secrets_cli/__init__.py
secrets_cli/requirements.txt
secrets_cli/secrets_cli.py
secrets_cli-0.1.3.dist-info/METADATA
secrets_cli-0.1.3.dist-info/WHEEL
secrets_cli-0.1.3.dist-info/entry_points.txt
secrets_cli-0.1.3.dist-info/RECORD
