Metadata-Version: 2.1
Name: secrets-cli
Version: 0.1.3
Summary: Run any applications with secrets stored in the Pangea Vault
Author: Pranav
Requires-Python: >=3.7.2,<4.0
Classifier: Programming Language :: Python :: 3
Classifier: Programming Language :: Python :: 3.8
Classifier: Programming Language :: Python :: 3.9
Classifier: Programming Language :: Python :: 3.10
Classifier: Programming Language :: Python :: 3.11
Requires-Dist: InquirerPy (==0.3.4)
Requires-Dist: pangea-sdk (==1.8.0)
Requires-Dist: typer[all] (==0.9.0)
